{"cameraMode":{"drawMode":0,"name":"Shaded","section":"Shading Mode"},"sceneLighting":true,"audioPlay":false,"sceneViewState":{"m_AlwaysRefresh":false,"showFog":true,"showSkybox":true,"showFlares":true,"showImageEffects":true,"showParticleSystems":true,"showVisualEffectGraphs":true,"m_FxEnabled":true},"in2DMode":false,"pivot":{"x":9.684576034545899,"y":11.271286010742188,"z":42.53376007080078},"rotation":{"x":-0.11058920621871948,"y":0.3251951336860657,"z":-0.03832288831472397,"w":-0.9383799433708191},"size":3.7382216453552248,"orthographic":false}